{
  "key": "삼해상사(부안1)_국판 씨푸드김_이물",
  "meta": {
    "last_updated": "2026-01-07",
    "warning_level": 0,
    "champion_model": null,
    "parent_stats": {
      "mean": 1.3333333333333333,
      "std": 1.1547005383792517,
      "slope": 1.0000000000000002,
      "avg_lag_days": 65.2
    }
  },
  "data": {
    "history": [
      {
        "date": "2023-10",
        "count": 0
      },
      {
        "date": "2023-11",
        "count": 2
      },
      {
        "date": "2023-12",
        "count": 3
      }
    ],
    "forecast": []
  },
  "children": [
    {
      "sub_key": "동물성이물",
      "stats": {
        "mean": 0.3333333333333333,
        "std": 0.5773502691896258,
        "slope": -6.551713670883651e-18,
        "avg_lag_days": 82.0
      },
      "history": [
        {
          "date": "2023-10",
          "count": 0
        },
        {
          "date": "2023-11",
          "count": 1
        },
        {
          "date": "2023-12",
          "count": 0
        }
      ]
    },
    {
      "sub_key": "벌레류",
      "stats": {
        "mean": 0.6666666666666666,
        "std": 1.1547005383792517,
        "slope": 1.0000000000000002,
        "avg_lag_days": 64.5
      },
      "history": [
        {
          "date": "2023-10",
          "count": 0
        },
        {
          "date": "2023-11",
          "count": 0
        },
        {
          "date": "2023-12",
          "count": 2
        }
      ]
    },
    {
      "sub_key": "합성수지류",
      "stats": {
        "mean": 0.3333333333333333,
        "std": 0.5773502691896258,
        "slope": -6.551713670883651e-18,
        "avg_lag_days": 50.0
      },
      "history": [
        {
          "date": "2023-10",
          "count": 0
        },
        {
          "date": "2023-11",
          "count": 1
        },
        {
          "date": "2023-12",
          "count": 1
        }
      ]
    }
  ]
}