{
  "key": "진천BC_PSPS_변질",
  "meta": {
    "last_updated": "2026-01-07",
    "warning_level": 0,
    "champion_model": null,
    "parent_stats": {
      "mean": 5.333333333333333,
      "std": 2.0816659994661326,
      "slope": -1.5000000000000007,
      "avg_lag_days": 134.6
    }
  },
  "data": {
    "history": [
      {
        "date": "2023-10",
        "count": 7
      },
      {
        "date": "2023-11",
        "count": 8
      },
      {
        "date": "2023-12",
        "count": 4
      }
    ],
    "forecast": []
  },
  "children": [
    {
      "sub_key": "곰팡이",
      "stats": {
        "mean": 5.0,
        "std": 1.7320508075688772,
        "slope": -1.5000000000000004,
        "avg_lag_days": 134.7
      },
      "history": [
        {
          "date": "2023-10",
          "count": 7
        },
        {
          "date": "2023-11",
          "count": 7
        },
        {
          "date": "2023-12",
          "count": 4
        }
      ]
    },
    {
      "sub_key": "기타변질",
      "stats": {
        "mean": 0.3333333333333333,
        "std": 0.5773502691896258,
        "slope": -6.551713670883651e-18,
        "avg_lag_days": 133.0
      },
      "history": [
        {
          "date": "2023-10",
          "count": 0
        },
        {
          "date": "2023-11",
          "count": 1
        },
        {
          "date": "2023-12",
          "count": 0
        }
      ]
    }
  ]
}